{
  "generated_at": "2026-02-13T12:47:30.732220+00:00",
  "model_version": "1.0.0",
  "metals": {
    "Gold": {
      "direction": "NEUTRAL",
      "confidence": 21,
      "composite_score": 48.5,
      "current_price": 4989.4,
      "forecast_5d": {
        "low": 4861.63,
        "mid": 5058.94,
        "high": 5264.26,
        "pct_change": 1.39
      },
      "forecast_20d": {
        "low": 4851.28,
        "mid": 5223.09,
        "high": 5623.4,
        "pct_change": 4.68
      },
      "squeeze_probability": 2,
      "regime": "RANGING",
      "signals": {
        "trend_momentum": {
          "score": 55.9,
          "details": "SMA5 > SMA20, MACD bearish, RSI 48, ROC(10) +5.8%"
        },
        "physical_stress": {
          "score": 42.6,
          "details": "Inventory z=-5.0, Delivery accel 0.4x, P/P 0.3:1, Coverage 183d"
        },
        "arima_model": {
          "score": 63.9,
          "details": "ARIMA(0, 1, 2) projects +1.4% over 5d"
        },
        "market_activity": {
          "score": 27.1,
          "details": "OI contracting 23.2%, volume normal"
        }
      },
      "key_drivers": [
        "Market Activity: bearish (OI contracting 23.2%, volume normal)",
        "Arima Model: bullish (ARIMA(0, 1, 2) projects +1.4% over 5d)",
        "Physical Stress: bearish (Inventory z=-5.0, Delivery accel 0.4x, P/P 0.3:1, Coverage 183d)"
      ],
      "anomalies": [],
      "correlations": {},
      "trend_indicators": {
        "sma5": 5007.88,
        "sma20": 4942.84,
        "sma50": 4606.66,
        "rsi": 47.5,
        "macd_bullish": "False",
        "macd_histogram": -17.4749,
        "bollinger_position": 0.562,
        "roc_10d": 5.84,
        "volatility_10d": 2.5646,
        "volatility_20d": 3.4974
      },
      "physical_signals": {
        "inventory_drawdown": {
          "z_score": -5.0,
          "change_5d": -1373362.93,
          "interpretation": "Rapid drawdown"
        },
        "delivery_acceleration": {
          "current_daily": 414,
          "avg_20d": 961.4,
          "acceleration_ratio": 0.43,
          "interpretation": "Below average"
        },
        "pp_squeeze": {
          "current_ratio": 0.33,
          "roc_5d_pct": -84.97,
          "squeeze_score": 1.6,
          "interpretation": "Low"
        },
        "coverage_erosion": {
          "coverage_days": 183.0,
          "avg_daily_delivery": 961.4,
          "interpretation": "Adequate"
        },
        "eligible_flow": {
          "registered_change_5d": -1373362.93,
          "eligible_change_5d": 65841.95,
          "interpretation": "Registered declining (drawdown)"
        }
      },
      "market_metrics": {
        "oi_10d_change_pct": -23.2,
        "volume_5d_avg": 10914.0,
        "volume_20d_avg": 10668.0,
        "volume_ratio": 1.02
      }
    },
    "Silver": {
      "direction": "NEUTRAL",
      "confidence": 21,
      "composite_score": 53.3,
      "current_price": 77.46,
      "forecast_5d": {
        "low": 72.41,
        "mid": 79.41,
        "high": 87.07,
        "pct_change": 2.51
      },
      "forecast_20d": {
        "low": 70.32,
        "mid": 83.62,
        "high": 99.44,
        "pct_change": 7.95
      },
      "squeeze_probability": 49,
      "regime": "RANGING",
      "signals": {
        "trend_momentum": {
          "score": 33.7,
          "details": "SMA5 < SMA20, MACD bearish, RSI 29, ROC(10) -1.1%"
        },
        "physical_stress": {
          "score": 59.0,
          "details": "Inventory z=-5.0, Delivery accel 0.0x, P/P 6.5:1, Coverage 89d"
        },
        "arima_model": {
          "score": 75.1,
          "details": "ARIMA(0, 1, 2) projects +2.5% over 5d"
        },
        "market_activity": {
          "score": 50.0,
          "details": "OI contracting 51.4%, volume elevated"
        }
      },
      "key_drivers": [
        "Arima Model: bullish (ARIMA(0, 1, 2) projects +2.5% over 5d)",
        "Trend Momentum: bearish (SMA5 < SMA20, MACD bearish, RSI 29, ROC(10) -1.1%)",
        "Physical Stress: bullish (Inventory z=-5.0, Delivery accel 0.0x, P/P 6.5:1, Coverage 89d)"
      ],
      "anomalies": [
        {
          "metric": "trading_volume",
          "z_score": 5.27,
          "description": "Unusually high trading volume (above normal by 5.3 std dev)"
        }
      ],
      "correlations": {},
      "trend_indicators": {
        "sma5": 79.81,
        "sma20": 89.69,
        "sma50": 78.17,
        "rsi": 29.4,
        "macd_bullish": "False",
        "macd_histogram": -2.5835,
        "bollinger_position": 0.274,
        "roc_10d": -1.05,
        "volatility_10d": 6.0526,
        "volatility_20d": 9.572
      },
      "physical_signals": {
        "inventory_drawdown": {
          "z_score": -5.0,
          "change_5d": -2622649.01,
          "interpretation": "Rapid drawdown"
        },
        "delivery_acceleration": {
          "current_daily": 0,
          "avg_20d": 228.8,
          "acceleration_ratio": 0.0,
          "interpretation": "Below average"
        },
        "pp_squeeze": {
          "current_ratio": 6.53,
          "roc_5d_pct": -0.99,
          "squeeze_score": 49.4,
          "interpretation": "Elevated"
        },
        "coverage_erosion": {
          "coverage_days": 88.7,
          "avg_daily_delivery": 228.8,
          "interpretation": "Tight"
        },
        "eligible_flow": {
          "registered_change_5d": -2622649.01,
          "eligible_change_5d": -16801920.46,
          "interpretation": "Registered declining (drawdown)"
        }
      },
      "market_metrics": {
        "oi_10d_change_pct": -51.39,
        "volume_5d_avg": 5115.0,
        "volume_20d_avg": 1700.0,
        "volume_ratio": 3.01
      }
    },
    "Copper": {
      "direction": "NEUTRAL",
      "confidence": 15,
      "composite_score": 54.3,
      "current_price": 5.74,
      "forecast_5d": {
        "low": 5.33,
        "mid": 5.74,
        "high": 6.18,
        "pct_change": 0.0
      },
      "forecast_20d": {
        "low": 4.95,
        "mid": 5.74,
        "high": 6.65,
        "pct_change": 0.0
      },
      "squeeze_probability": 23,
      "regime": "RANGING",
      "signals": {
        "trend_momentum": {
          "score": 42.1,
          "details": "SMA5 < SMA20, MACD bearish, RSI 43, ROC(10) -2.6%"
        },
        "physical_stress": {
          "score": 47.8,
          "details": "Inventory z=5.0, Delivery accel 1.0x, P/P 4.9:1, Coverage 0d"
        },
        "arima_model": {
          "score": 50.0,
          "details": "ARIMA(0, 1, 0) projects +0.0% over 5d"
        },
        "market_activity": {
          "score": 99.9,
          "details": "OI expanding 162.4%, volume elevated"
        }
      },
      "key_drivers": [
        "Market Activity: bullish (OI expanding 162.4%, volume elevated)",
        "Trend Momentum: bearish (SMA5 < SMA20, MACD bearish, RSI 43, ROC(10) -2.6%)",
        "Physical Stress: bearish (Inventory z=5.0, Delivery accel 1.0x, P/P 4.9:1, Coverage 0d)"
      ],
      "anomalies": [
        {
          "metric": "trading_volume",
          "z_score": 5.26,
          "description": "Unusually high trading volume (above normal by 5.3 std dev)"
        }
      ],
      "correlations": {},
      "trend_indicators": {
        "sma5": 5.86,
        "sma20": 5.87,
        "sma50": 5.69,
        "rsi": 43.5,
        "macd_bullish": "False",
        "macd_histogram": -0.0324,
        "bollinger_position": 0.222,
        "roc_10d": -2.65,
        "volatility_10d": 2.3942,
        "volatility_20d": 2.5249
      },
      "physical_signals": {
        "inventory_drawdown": {
          "z_score": 5.0,
          "change_5d": 29600.0,
          "interpretation": "Building"
        },
        "delivery_acceleration": {
          "current_daily": 338,
          "avg_20d": 332.0,
          "acceleration_ratio": 1.02,
          "interpretation": "Normal"
        },
        "pp_squeeze": {
          "current_ratio": 4.87,
          "roc_5d_pct": -48.89,
          "squeeze_score": 23.4,
          "interpretation": "Moderate"
        },
        "coverage_erosion": {
          "coverage_days": 0.1,
          "avg_daily_delivery": 332.0,
          "interpretation": "Critical"
        },
        "eligible_flow": {
          "registered_change_5d": 29600.0,
          "eligible_change_5d": -13266.0,
          "interpretation": "Eligible \u2192 Registered (delivery intent)"
        }
      },
      "market_metrics": {
        "oi_10d_change_pct": 162.42,
        "volume_5d_avg": 6799.0,
        "volume_20d_avg": 2558.0,
        "volume_ratio": 2.66
      }
    },
    "Platinum": {
      "direction": "NEUTRAL",
      "confidence": 11,
      "composite_score": 51.8,
      "current_price": 2018.7,
      "forecast_5d": {
        "low": 1888.3,
        "mid": 2045.89,
        "high": 2216.63,
        "pct_change": 1.35
      },
      "forecast_20d": {
        "low": 1820.82,
        "mid": 2129.36,
        "high": 2490.19,
        "pct_change": 5.48
      },
      "squeeze_probability": 66,
      "regime": "RANGING",
      "signals": {
        "trend_momentum": {
          "score": 32.7,
          "details": "SMA5 < SMA20, MACD bearish, RSI 21, ROC(10) -4.0%"
        },
        "physical_stress": {
          "score": 40.9,
          "details": "Delivery accel 0.0x, P/P 10.8:1, Coverage 184d"
        },
        "arima_model": {
          "score": 63.5,
          "details": "ARIMA(1, 1, 0) projects +1.4% over 5d"
        },
        "market_activity": {
          "score": 100.0,
          "details": "OI expanding 38.7%, volume elevated"
        }
      },
      "key_drivers": [
        "Market Activity: bullish (OI expanding 38.7%, volume elevated)",
        "Trend Momentum: bearish (SMA5 < SMA20, MACD bearish, RSI 21, ROC(10) -4.0%)",
        "Arima Model: bullish (ARIMA(1, 1, 0) projects +1.4% over 5d)"
      ],
      "anomalies": [
        {
          "metric": "trading_volume",
          "z_score": 5.28,
          "description": "Unusually high trading volume (above normal by 5.3 std dev)"
        }
      ],
      "correlations": {},
      "trend_indicators": {
        "sma5": 2074.22,
        "sma20": 2307.44,
        "sma50": 2153.29,
        "rsi": 20.6,
        "macd_bullish": "False",
        "macd_histogram": -50.7329,
        "bollinger_position": 0.225,
        "roc_10d": -4.0,
        "volatility_10d": 3.1429,
        "volatility_20d": 6.1565
      },
      "physical_signals": {
        "delivery_acceleration": {
          "current_daily": 0,
          "avg_20d": 34.7,
          "acceleration_ratio": 0.0,
          "interpretation": "Below average"
        },
        "pp_squeeze": {
          "current_ratio": 10.81,
          "roc_5d_pct": -3.02,
          "squeeze_score": 65.9,
          "interpretation": "Extreme"
        },
        "coverage_erosion": {
          "coverage_days": 184.4,
          "avg_daily_delivery": 34.7,
          "interpretation": "Adequate"
        },
        "eligible_flow": {
          "registered_change_5d": -6955.94,
          "eligible_change_5d": -14933.79,
          "interpretation": "Registered declining (drawdown)"
        }
      },
      "market_metrics": {
        "oi_10d_change_pct": 38.66,
        "volume_5d_avg": 1135.0,
        "volume_20d_avg": 330.0,
        "volume_ratio": 3.44
      }
    },
    "Palladium": {
      "direction": "BULLISH",
      "confidence": 18,
      "composite_score": 62.4,
      "current_price": 1655.5,
      "forecast_5d": {
        "low": 1525.9,
        "mid": 1654.58,
        "high": 1794.11,
        "pct_change": -0.06
      },
      "forecast_20d": {
        "low": 1413.71,
        "mid": 1654.58,
        "high": 1936.49,
        "pct_change": -0.06
      },
      "squeeze_probability": 93,
      "regime": "RANGING",
      "signals": {
        "trend_momentum": {
          "score": 32.8,
          "details": "SMA5 < SMA20, MACD bearish, RSI 26, ROC(10) -1.9%"
        },
        "physical_stress": {
          "score": 79.2,
          "details": "P/P 11.1:1"
        },
        "arima_model": {
          "score": 49.4,
          "details": "ARIMA(1, 1, 0) projects -0.1% over 5d"
        },
        "market_activity": {
          "score": 100.0,
          "details": "OI expanding 48.8%, volume elevated"
        }
      },
      "key_drivers": [
        "Market Activity: bullish (OI expanding 48.8%, volume elevated)",
        "Physical Stress: bullish (P/P 11.1:1)",
        "Trend Momentum: bearish (SMA5 < SMA20, MACD bearish, RSI 26, ROC(10) -1.9%)"
      ],
      "anomalies": [
        {
          "metric": "trading_volume",
          "z_score": 5.29,
          "description": "Unusually high trading volume (above normal by 5.3 std dev)"
        }
      ],
      "correlations": {},
      "trend_indicators": {
        "sma5": 1700.18,
        "sma20": 1815.61,
        "sma50": 1745.52,
        "rsi": 26.4,
        "macd_bullish": "False",
        "macd_histogram": -27.1831,
        "bollinger_position": 0.225,
        "roc_10d": -1.94,
        "volatility_10d": 2.3297,
        "volatility_20d": 6.0662
      },
      "physical_signals": {
        "pp_squeeze": {
          "current_ratio": 11.12,
          "roc_5d_pct": 93.05,
          "squeeze_score": 93.4,
          "interpretation": "Extreme"
        },
        "eligible_flow": {
          "registered_change_5d": 5600.72,
          "eligible_change_5d": -27193.52,
          "interpretation": "Eligible \u2192 Registered (delivery intent)"
        }
      },
      "market_metrics": {
        "oi_10d_change_pct": 48.77,
        "volume_5d_avg": 296.0,
        "volume_20d_avg": 84.0,
        "volume_ratio": 3.52
      }
    }
  }
}